AsposePDFPython/3rdParty.pdf
AsposePDFPython/LICENSE
AsposePDFPython/__init__.py
AsposePDFPythonWrappers/__init__.py
AsposePDFPythonWrappers/artifact.py
AsposePDFPythonWrappers/artifact_collection.py
AsposePDFPythonWrappers/base_paragraph.py
AsposePDFPythonWrappers/color.py
AsposePDFPythonWrappers/document.py
AsposePDFPythonWrappers/file_hyperlink.py
AsposePDFPythonWrappers/hyperlink.py
AsposePDFPythonWrappers/image.py
AsposePDFPythonWrappers/image_stamp.py
AsposePDFPythonWrappers/layer.py
AsposePDFPythonWrappers/license.py
AsposePDFPythonWrappers/local_hyperlink.py
AsposePDFPythonWrappers/margin_info.py
AsposePDFPythonWrappers/note.py
AsposePDFPythonWrappers/page.py
AsposePDFPythonWrappers/page_collection.py
AsposePDFPythonWrappers/page_number_stamp.py
AsposePDFPythonWrappers/paragraphs.py
AsposePDFPythonWrappers/point.py
AsposePDFPythonWrappers/rectangle.py
AsposePDFPythonWrappers/stamp.py
AsposePDFPythonWrappers/text_stamp.py
AsposePDFPythonWrappers/web_hyperlink.py
AsposePDFPythonWrappers/devices/__init__.py
AsposePDFPythonWrappers/devices/device.py
AsposePDFPythonWrappers/devices/image_device.py
AsposePDFPythonWrappers/devices/jpeg_device.py
AsposePDFPythonWrappers/devices/page_device.py
AsposePDFPythonWrappers/devices/png_device.py
AsposePDFPythonWrappers/devices/resolution.py
AsposePDFPythonWrappers/facades/__init__.py
AsposePDFPythonWrappers/facades/facade.py
AsposePDFPythonWrappers/facades/formatted_text.py
AsposePDFPythonWrappers/facades/pdf_extractor.py
AsposePDFPythonWrappers/facades/stamp.py
AsposePDFPythonWrappers/operators/__init__.py
AsposePDFPythonWrappers/operators/close_path_fill_stroke.py
AsposePDFPythonWrappers/operators/fill_stroke.py
AsposePDFPythonWrappers/operators/operator.py
AsposePDFPythonWrappers/sys/collection/__init__.py
AsposePDFPythonWrappers/sys/collection/list.py
AsposePDFPythonWrappers/sys/drawing/__init__.py
AsposePDFPythonWrappers/sys/drawing/color.py
AsposePDFPythonWrappers/sys/drawing/gradient_radial_shading.py
Aspose_PDF_Python_Via_Cpp_windows_x64-1.0.dist-info/METADATA
Aspose_PDF_Python_Via_Cpp_windows_x64-1.0.dist-info/WHEEL
Aspose_PDF_Python_Via_Cpp_windows_x64-1.0.dist-info/top_level.txt
Aspose_PDF_Python_Via_Cpp_windows_x64-1.0.dist-info/RECORD
